<?xml version="1.0" encoding="UTF-8"?>
<objects serializationModel="Studio.02.02.00">
	<object class="AudioFile" id="{88a1ebb7-f3cd-436c-b900-e44c103afc43}">
		<property name="assetPath">
			<value>75579-Jail_door_cell_block_key_twist_unlock-BLASTWAVEFX-11104.wav</value>
		</property>
		<property name="frequencyInKHz">
			<value>44.0999985</value>
		</property>
		<property name="channelCount">
			<value>2</value>
		</property>
		<property name="length">
			<value>0.74612244897959179</value>
		</property>
		<relationship name="masterAssetFolder">
			<destination>{7bca2572-fc01-4ae5-b612-e32c2763b443}</destination>
		</relationship>
	</object>
</objects>
