<?xml version="1.0" encoding="UTF-8"?>
<objects serializationModel="Studio.02.02.00">
	<object class="AudioFile" id="{98ae9338-ea5b-4d7d-91cb-3ebed45d85f7}">
		<property name="assetPath">
			<value>201657-EFX_INT_Combination_Two_Metal_02_A.wav</value>
		</property>
		<property name="isStreaming">
			<value>true</value>
		</property>
		<property name="frequencyInKHz">
			<value>96</value>
		</property>
		<property name="channelCount">
			<value>2</value>
		</property>
		<property name="length">
			<value>12.7865</value>
		</property>
		<relationship name="masterAssetFolder">
			<destination>{7bca2572-fc01-4ae5-b612-e32c2763b443}</destination>
		</relationship>
	</object>
</objects>
